lgpdXml/__init__.py
lgpdXml-0.0.3.dist-info/LICENSE
lgpdXml-0.0.3.dist-info/METADATA
lgpdXml-0.0.3.dist-info/WHEEL
lgpdXml-0.0.3.dist-info/top_level.txt
lgpdXml-0.0.3.dist-info/RECORD
