Metadata-Version: 2.1
Name: lgpdXml
Version: 0.0.3
Summary: An simple and easy method to find and replace values of xml
Home-page: https://github.com/claudiotorresarbe/lgpdXml
Author: Claudio Torres Arbe
Author-email: claudiotarbe@gmail.com
License: UNKNOWN
Platform: UNKNOWN
Classifier: Programming Language :: Python :: 3.8
Classifier: License :: OSI Approved :: MIT License
Classifier: Operating System :: OS Independent
Requires-Python: >=3.6
